{"user":"obama","location":{"type":"Feature","properties":{"SCALERANK":6,"NATSCALE":30,"LABELRANK":6,"FEATURECLA":"Populated place","NAME":"Ayakoz","NAMEPAR":null,"NAMEALT":null,"DIFFASCII":0,"NAMEASCII":"Ayakoz","ADM0CAP":0,"CAPALT":0,"CAPIN":null,"WORLDCITY":0,"MEGACITY":0,"SOV0NAME":"Kazakhstan","SOV_A3":"KAZ","ADM0NAME":"Kazakhstan","ADM0_A3":"KAZ","ADM1NAME":"East Kazakhstan","ISO_A2":"KZ","NOTE":null,"LATITUDE":47.964732,"LONGITUDE":80.429705,"CHANGED":1,"NAMEDIFF":0,"DIFFNOTE":"Changed scale rank.","POP_MAX":45861,"POP_MIN":33479,"POP_OTHER":45861,"RANK_MAX":7,"RANK_MIN":7,"GEONAMEID":1525988,"MEGANAME":null,"LS_NAME":"Ayakoz","LS_MATCH":1,"CHECKME":0,"MAX_POP10":45861,"MAX_POP20":45861,"MAX_POP50":0,"MAX_POP300":0,"MAX_POP310":0,"MAX_NATSCA":20,"MIN_AREAKM":16,"MAX_AREAKM":16,"MIN_AREAMI":6,"MAX_AREAMI":6,"MIN_PERKM":19,"MAX_PERKM":19,"MIN_PERMI":12,"MAX_PERMI":12,"MIN_BBXMIN":80.408333,"MAX_BBXMIN":80.408333,"MIN_BBXMAX":80.458333,"MAX_BBXMAX":80.458333,"MIN_BBYMIN":47.941667,"MAX_BBYMIN":47.941667,"MIN_BBYMAX":47.991667,"MAX_BBYMAX":47.991667,"MEAN_BBXC":80.434821,"MEAN_BBYC":47.965179,"COMPARE":0,"GN_ASCII":"Ayakoz","FEATURE_CL":"P","FEATURE_CO":"PPL","ADMIN1_COD":15,"GN_POP":33479,"ELEVATION":0,"GTOPO30":654,"TIMEZONE":"Asia/Almaty","GEONAMESNO":"Geonames ascii name + lat.d + long.d matching.","UN_FID":0,"UN_ADM0":null,"UN_LAT":0,"UN_LONG":0,"POP1950":0,"POP1955":0,"POP1960":0,"POP1965":0,"POP1970":0,"POP1975":0,"POP1980":0,"POP1985":0,"POP1990":0,"POP1995":0,"POP2000":0,"POP2005":0,"POP2010":0,"POP2015":0,"POP2020":0,"POP2025":0,"POP2050":0,"CITYALT":null},"geometry":{"type":"Point","coordinates":[80.42970536186289,47.96473248197918]}},"text":"yoyo","timestamp":"2014-12-04T21:32:16.455Z"}